gctl/__init__.py
gctl/curve_generator.py
gctl/curve/dubins_path.py
gctl/curve/reeds_shepp.py
gctl-1.2.dist-info/LICENSE
gctl-1.2.dist-info/METADATA
gctl-1.2.dist-info/WHEEL
gctl-1.2.dist-info/top_level.txt
gctl-1.2.dist-info/RECORD
