Metadata-Version: 2.1
Name: gctl
Version: 1.2
Summary: Generate curve tool
Author-email: Han Ruihua <hanrh@connect.hku.hk>
Project-URL: Homepage, https://github.com/hanruihua/GenerateCurveTool
Classifier: Programming Language :: Python :: 3
Classifier: License :: OSI Approved :: MIT License
Classifier: Operating System :: OS Independent
Requires-Python: >=3.7
License-File: LICENSE
Requires-Dist: matplotlib
Requires-Dist: numpy
Requires-Dist: scipy
